eodag_cube/__init__.py
eodag_cube/py.typed
eodag_cube/api/__init__.py
eodag_cube/api/product/__init__.py
eodag_cube/api/product/_assets.py
eodag_cube/api/product/_product.py
eodag_cube/api/product/drivers/__init__.py
eodag_cube/api/product/drivers/generic.py
eodag_cube/api/product/drivers/sentinel2_l1c.py
eodag_cube/api/product/drivers/stac_assets.py
eodag_cube/types/__init__.py
eodag_cube/utils/__init__.py
eodag_cube/utils/exceptions.py
eodag_cube/utils/xarray.py
eodag_cube-0.6.3.dist-info/licenses/LICENSE
eodag_cube-0.6.3.dist-info/licenses/NOTICE
eodag_cube-0.6.3.dist-info/METADATA
eodag_cube-0.6.3.dist-info/WHEEL
eodag_cube-0.6.3.dist-info/top_level.txt
eodag_cube-0.6.3.dist-info/RECORD
