Metadata-Version: 2.4
Name: eodag_cube
Version: 0.6.3
Summary: Data access for EODAG
Author-email: CS GROUP - France <eodag@csgroup.space>
License: Apache 2.0
Project-URL: Repository, https://github.com/CS-SI/eodag-cube
Classifier: Development Status :: 5 - Production/Stable
Classifier: Intended Audience :: Developers
Classifier: Intended Audience :: Science/Research
Classifier: Natural Language :: English
Classifier: License :: OSI Approved :: Apache Software License
Classifier: Programming Language :: Python
Classifier: Programming Language :: Python :: 3
Classifier: Programming Language :: Python :: 3.9
Classifier: Programming Language :: Python :: 3.10
Classifier: Programming Language :: Python :: 3.11
Classifier: Programming Language :: Python :: 3.12
Classifier: Programming Language :: Python :: 3.13
Classifier: Programming Language :: Python :: Implementation :: CPython
Classifier: Topic :: Scientific/Engineering :: GIS
Requires-Python: >=3.9
License-File: LICENSE
License-File: NOTICE
Requires-Dist: eodag>=3.9.0
Requires-Dist: numpy
Requires-Dist: rasterio
Requires-Dist: xarray
Requires-Dist: rioxarray
Requires-Dist: h5netcdf
Requires-Dist: netcdf4
Requires-Dist: cfgrib
Requires-Dist: fsspec
Requires-Dist: s3fs
Requires-Dist: aiohttp
Provides-Extra: dev
Requires-Dist: flake8; extra == "dev"
Requires-Dist: isort; extra == "dev"
Requires-Dist: pre-commit; extra == "dev"
Requires-Dist: pytest; extra == "dev"
Requires-Dist: pytest-cov; extra == "dev"
Requires-Dist: tox; extra == "dev"
Requires-Dist: tox-uv; extra == "dev"
Requires-Dist: nose; extra == "dev"
Requires-Dist: faker; extra == "dev"
Requires-Dist: coverage; extra == "dev"
Requires-Dist: moto>=5; extra == "dev"
Requires-Dist: responses!=0.24.0; extra == "dev"
Requires-Dist: twine; extra == "dev"
Requires-Dist: wheel; extra == "dev"
Requires-Dist: mypy; extra == "dev"
Requires-Dist: types-requests; extra == "dev"
Requires-Dist: types-shapely; extra == "dev"
Requires-Dist: boto3-stubs[essential]; extra == "dev"
Dynamic: license-file
